[
 {
  "id": 1,
  "nombre": "Lourdes Andrea ",
  "apellido": " Bustos",
  "emailU": "lourdesabustos@gmail.com",
  "contrasena": "nose1302"
 },
 {
  "id": 2,
  "nombre": "Pepito",
  "apellido": "Aurelio",
  "emailU": "pepito.aurelio@gmail.com",
  "contrasena": "dieta18"
 },
 {
  "id": 3,
  "nombre": "Bruno",
  "apellido": "Bustos",
  "emailU": "lourdesabustos@gmail.com",
  "contrasena": [
   "sdasdasdad",
   "sadasdSFASF"
  ]
 },
 {
  "id": 4,
  "nombre": "Bruno",
  "apellido": "Bustos",
  "emailU": "lourdesabustos@gmail.com",
  "contrasena": [
   "NOSE1302",
   "NOSE1302"
  ]
 }
]